zhue
