Metadata-Version: 1.0
Name: zhue
Version: 0.9.5
Summary: Python SDK for Philips Hue devices
Home-page: https://github.com/pschmitt/zhue
Author: Philipp Schmitt
Author-email: philipp@schmitt.co
License: GPL3
Platform: UNKNOWN
